omninet_pytorch/__init__.py
omninet_pytorch/omninet_pytorch.py
omninet_pytorch-0.0.6.dist-info/LICENSE
omninet_pytorch-0.0.6.dist-info/METADATA
omninet_pytorch-0.0.6.dist-info/WHEEL
omninet_pytorch-0.0.6.dist-info/top_level.txt
omninet_pytorch-0.0.6.dist-info/RECORD
