Metadata-Version: 2.1
Name: omninet-pytorch
Version: 0.0.6
Summary: Omninet - Pytorch
Home-page: https://github.com/lucidrains/omninet-pytorch
Author: Phil Wang
Author-email: lucidrains@gmail.com
License: MIT
Keywords: artificial intelligence,deep learning,transformer,attention mechanism
Platform: UNKNOWN
Classifier: Development Status :: 4 - Beta
Classifier: Intended Audience :: Developers
Classifier: Topic :: Scientific/Engineering :: Artificial Intelligence
Classifier: License :: OSI Approved :: MIT License
Classifier: Programming Language :: Python :: 3.6
Requires-Dist: einops (>=0.3)
Requires-Dist: torch (>=1.6)
Requires-Dist: performer-pytorch
